adbnativeblitz/README.MD
adbnativeblitz/__init__.py
adbnativeblitz/requirements.txt
adbnativeblitz/thirdparty.json
adbnativeblitz-0.11.dist-info/LICENSE.rst
adbnativeblitz-0.11.dist-info/METADATA
adbnativeblitz-0.11.dist-info/WHEEL
adbnativeblitz-0.11.dist-info/top_level.txt
adbnativeblitz-0.11.dist-info/RECORD
