Metadata-Version: 2.1
Name: adbnativeblitz
Version: 0.11
Summary: ADB Screenshots as fast as scrcpy, but 100% native!
Home-page: https://github.com/hansalemaos/adbnativeblitz
Author: Johannes Fischer
Author-email: aulasparticularesdealemaosp@gmail.com
License: MIT
Keywords: adb,screenshots,scrcpy
Classifier: Development Status :: 4 - Beta
Classifier: Programming Language :: Python :: 3 :: Only
Classifier: Programming Language :: Python :: 3.10
Classifier: Topic :: Software Development :: Libraries :: Python Modules
Classifier: Topic :: Utilities
License-File: LICENSE.rst
Requires-Dist: av
